Metadata-Version: 2.0
Name: odoo10-addon-stock-analytic
Version: 10.0.1.0.1
Summary: Adds an analytic account in stock move
Home-page: http://www.julius.fr/
Author: Julius Network Solutions,ClearCorp, OpenSynergy Indonesia,Odoo Community Association (OCA)
Author-email: support@odoo-community.org
License: AGPL-3
Platform: UNKNOWN
Classifier: Programming Language :: Python
Classifier: Framework :: Odoo
Classifier: License :: OSI Approved :: GNU Affero General Public License v3
Requires-Python: ~=2.7
Requires-Dist: odoo (<10.1dev,>=10.0)
Requires-Dist: odoo10-addon-procurement-analytic
